{
  "_format": "hh-sol-cache-2",
  "files": {
    "/Users/packer/Documents/github/hello-web3/contracts/Counter.sol": {
      "lastModificationDate": 1646129309848,
      "contentHash": "29b285d2b2d1686f936553a09f7b7305",
      "sourceName": "contracts/Counter.sol",
      "solcConfig": {
        "version": "0.8.4",
        "settings": {
          "optimizer": {
            "enabled": false,
            "runs": 200
          },
          "outputSelection": {
            "*": {
              "*": [
                "abi",
                "evm.bytecode",
                "evm.deployedBytecode",
                "evm.methodIdentifiers",
                "metadata"
              ],
              "": [
                "ast"
              ]
            }
          }
        }
      },
      "imports": [
        "hardhat/console.sol"
      ],
      "versionPragmas": [
        "^0.8.0"
      ],
      "artifacts": [
        "Counter"
      ]
    },
    "/Users/packer/Documents/github/hello-web3/node_modules/hardhat/console.sol": {
      "lastModificationDate": 1646127829796,
      "contentHash": "cc4777addd464ea56fa35b1c45df0591",
      "sourceName": "hardhat/console.sol",
      "solcConfig": {
        "version": "0.8.4",
        "settings": {
          "optimizer": {
            "enabled": false,
            "runs": 200
          },
          "outputSelection": {
            "*": {
              "*": [
                "abi",
                "evm.bytecode",
                "evm.deployedBytecode",
                "evm.methodIdentifiers",
                "metadata"
              ],
              "": [
                "ast"
              ]
            }
          }
        }
      },
      "imports": [],
      "versionPragmas": [
        ">=0.4.22 <0.9.0"
      ],
      "artifacts": [
        "console"
      ]
    }
  }
}
